bao
tool
