Metadata-Version: 1.0
Name: bao
Version: 1.0.4
Summary: this is my first test
Home-page: https://www.bilibili.com/
Author: xushibo
Author-email: 937207118@qq.com
License: UNKNOWN
Platform: UNKNOWN
